MANIFEST.in
README.rst
setup.py
pyinrail/pyinrail.py
pyinrail/stations.json
pyinrail/trains.json
pyinrail/utils.py
pyinrail.egg-info/PKG-INFO
pyinrail.egg-info/SOURCES.txt
pyinrail.egg-info/dependency_links.txt
pyinrail.egg-info/not-zip-safe
pyinrail.egg-info/requires.txt
pyinrail.egg-info/top_level.txt