Metadata-Version: 1.1
Name: pyinrail
Version: 1.0.0
Summary: Python Wrapper for Indian Railways Enquiry API
Home-page: https://github.com/nikhilkumarsingh/pyinrail
Author: Nikhil Kumar Singh
Author-email: nikhilksingh97@gmail.com
License: MIT
Keywords: indian railways enquiry api wrapper
Platform: UNKNOWN
Classifier: Development Status :: 4 - Beta
Classifier: License :: OSI Approved :: MIT License
Classifier: Programming Language :: Python
Classifier: Programming Language :: Python :: 3
Classifier: Programming Language :: Python :: 3.3
Classifier: Programming Language :: Python :: 3.4
Classifier: Programming Language :: Python :: 3.5
Classifier: Programming Language :: Python :: 3.6
